{
    "Shipment manifested": "No Action",
    "Delivered": "Notify",
    "Package on hold for delivery": "Action (Receiver)",
    "Out for delivery": "Notify",
    "Delivery issue resolved. Delivery will be scheduled for the next working day": "Notify",
    "Shipment collected": "Notify",
    "Warehouse Scan": "No Action",
    "In Transit": "No Action",
    "Collection failed. To be rescheduled.": "Action (Sender)",
    "Collection failed or cancelled. Rebooking required": "Action (Sender)",
    "Collection failed - Parcel not ready": "Action (Sender)",
    "Collection failed - Shipper not available": "Action (Sender)",
    "Collection failed": "Action (Sender)",
    "Collection made - label issue": "Action (internal)",
    "Package not collected - Damaged": "Action (Sender)",
    "Not collected": "Action (Sender)",
    "Collection failed - Unable to gain access": "Action (Sender)",
    "Collection scheduled": "Action (Sender)",
    "Collection scheduled for next business day": "Action (Sender)",
    "Not collected due to address issue": "Action (Sender)",
    "Arrival at delivery depot": "No Action",
    "Import Scan": "No Action",
    "Shipment dropped off awaiting carrier collection": "Notify",
    "Export Scan": "No Action",
    "Released by customs. Clearance complete.": "No Action",
    "Delivery attempted. Receiver not available for delivery. Shipment to be delivered to a nearby pick-up point.": "Notify",
    "Shipment ready for collection from pick-up point": "Notify",
    "1st of 3 Delivery attempts. Receiver not available": "Notify",
    "Delivery rescheduled": "Notify",
    "Customs clearance in progress": "No Action",
    "Delay due to adverse weather conditions": "Notify",
    "Request to reschedule delivery": "No Action",
    "Awaiting release from customs": "No Action",
    "Missing or incomplete export documentation": "Action (Sender)",
    "Shipment to be returned": "Action (internal)",
    "Delivery to pick-up point pending": "No Action",
    "Delayed due to circumstances beyond our control - Corrective action underway": "Notify",
    "Correct company or receiver name needed for delivery": "Action (Sender)",
    "Held awaiting tax payment by the receiver": "Action (Receiver)",
    "Valid receiver's tax ID required for customs clearance": "Action (Receiver)",
    "Carrier misrouted the shipment - Corrective action underway": "Notify",
    "Billing information received": "No Action",
    "Incomplete or incorrect delivery address. Additional information or directions needed for delivery.": "Action (Sender)",
    "Delivery to alternative address requested": "No action",
    "Final delivery attempt. Shipment to be returned.": "Notify",
    "Delivery scheduled for next business day": "No action",
    "Carrier error delayed delivery": "Notify",
    "Shipment is held to verify commodity description for correct classification": "Action (Sender)",
    "Delivery attempted. Security access needed for delivery.": "Action (Sender)",
    "Carrier to contact sender or receiver": "Notify",
    "Address located in remote area where deliveries not made daily": "Notify",
    "Held for inspection by government agency": "Notify",
    "2nd delivery attempt. Receiver not available.": "Notify",
    "Return label left with the receiver": "No action",
    "Delivery refused": "Action (Sender)",
    "Delay due to flight cancelled or delayed": "Notify",
    "Receiver moved": "Action (Sender)",
    "Handover to broker for clearance": "No action",
    "Information needed from the receiver": "Action (Receiver)",
    "Receiver to pick up shipment": "Action (Receiver)",
    "Investigation opened for lost package": "No action",
    "Power of attorney documentation missing": "Action (Sender)",
    "Tax payment received": "No action",
    "Package damaged in transit": "Action (Sender)",
    "Unable to deliver to pick-up point - Re-attempt on the next business day": "Notify",
    "1st delivery attempt. Unable to collect tax payment.": "Action (Receiver)",
    "A late trailer arrival has delayed delivery - Delivery may be delayed by 24 hours": "Notify",
    "Return parcel now delivered back to sender": "Action (Internal)",
    "Shipment to be held and receiver to be contacted for clearance instructions": "Action (Receiver)",
    "Delivery to pick-up point requested": "Notify",
    "Shipment cannot be held any longer to pick-up location": "Escalate to Support",
    "Delivery attempted. Receiver not available for delivery. Delivery rescheduled.": "Action (Sender)",
    "We are awaiting 'return to sender' authorisation": "Action (Internal)",
    "Package was cleared after the scheduled departure. Expect a 1 business day delay": "Notify",
    "Return of the package requested": "Action (Sender)",
    "Due to commodity or weight, your package is being held to verify value.": "Action (Sender)",
    "Missing export license required for clearance": "Action (Sender)",
    "Clearance has been delayed by customs or other government agency": "Notify",
    "Arrived late at destination - Expect 1 business day delivery delay": "Notify",
    "Contact with sender made": "No Action",
    "Additional information required for customs clearance": "Action (Receiver)",
    "Transferred to Post Office for delivery, delivery may be delayed by up to 2 business days": "Notify",
    "Package needs to be collected within 5 business days": "Action (Receiver)",
    "Claim issued": "Escalate to Support",
    "Receiver contact attempt for pickup arrangements": "Notify",
    "Unable to deliver to pick-up point - Re-attempt delivery to the receiver's address": "Notify",
    "Delivery attempted. Receiver not available for delivery": "Action (Sender)",
    "Package has been re-directed to the destination": "Notify",
    "Valid receiver's contact information required": "Action (Receiver)",
    "Shipment on hold after request": "No Action",
    "Shipment on hold due to restricted items": "Escalate to Support",
    "Personal affects form required for customs clearance": "Action (Receiver)",
    "Delivery rescheduled due to holiday closures": "Notify",
    "Unable to contact receiver": "Action (Sender)",
    "New instructions received - We updated the delivery information for your package": "Notify",
    "Shipment was not processed by brokerage. This has caused a delay": "Notify",
    "The returned package requires an export invoice for duty relief": "Action (Sender)",
    "Carrier is unable to deliver to the PO Box address and is attempting to locate an alternative address": "Action (Sender)",
    "1st delivery attempt. No adult signature. Delivery rescheduled.": "Action (Sender)",
    "Shipment cannot be held any longer": "Escalate to Support",
    "Trying to contact receiver": "No action",
    "Service not available for this location and will be changed": "Escalate to Support",
    "Damaged package being returned": "Action (Sender)",
    "The receiver wishes to use their own broker for customs clearance. This may delay delivery": "Action (Receiver)",
    "1st collection attempt. Package not ready. 2nd collection attempt to be made.": "Notify",
    "To be delivered today": "Notify",
    "The request for this package was cancelled": "No Action",
    "Package could not be located for intercept": "Escalate to Support",
    "Customs clearance delay": "Notify",
    "Missing import license required for clearance": "Action (Sender)",
    "As requested, the package was transferred to a free trade zone or a recipient nominated broker.": "Notify",
    "2nd delivery attempt. Unable to collect tax payment.": "Action (Receiver)",
    "Unique customs identification number missing required for clearance": "Action (Sender)",
    "Request to contact carrier": "Notify",
    "Contents damaged and balance being returned": "Action (Sender)",
    "Shipment not collected by receiver from pick-up point and will be returned to sender": "Action (Internal)",
    "Damaged contents to be discarded": "Action (Sender)",
    "Package not arrived at destination": "Action (Sender)",
    "Destination address not served": "Action (Sender)",
    "Delivery scheduled for a future date": "Notify",
    "Final delivery attempt. Unable to collect tax payment.": "Action (Sender)",
    "Unable to deliver to PO box. Package to be returned.": "Action (Sender)",
    "Scheduled for delivery": "Notify",
    "Shipment on hold": "No Action",
    "Delivery delayed due to a traffic related issue": "Notify",
    "Additional information or paperwork required for customs clearance": "Action (Sender)",
    "Change of delivery address": "Notify",
    "Delivery attempted. Receiver's location vacant.": "Action (Sender)",
    "Unable to access premises. Delivery to be rescheduled.": "Action (Sender)",
    "On hold - Pending delivery book-in with receiver (Scheduled delivery)": "Action (Receiver)",
    "Shipment returned or being returned to sender": "Action (Sender)",
    "Package damaged - On hold": "Action (Sender)",
    "Customs cleareance delay - Formal entry - Additional processing may delay delivery": "Notify",
    "Shipment delivered with possible damage": "Notify",
    "Shipment is held due to unrealistic value": "Action (Sender)",
    "Delay due to mechanical failure": "Notify",
    "Package damaged in transit - Chemical or Dangerous goods": "Escalate to Support",
    "Still awaiting further instructions": "Action (Internal)",
    "2nd delivery attempt. No adult signature. Delivery rescheduled.": "Action (Sender)",
    "The country of origin is required on the invoice before the shipment can be released": "Action (Sender)",
    "Importer disputes the value or other information on invoice; shipment held to verify accuracy with shipper": "Action (Sender)",
    "Transit or bond documentation is missing and is required for clearance. We are working to obtain this information": "Escalate to Support",
    "Missing Certificate of Origin": "Action (Sender)",
    "The recipient must provide their unique customs ID number for customs clearance": "Action (Receiver)",
    "The shipment value or currency is missing from the invoice and is required for clearance.": "Action (Sender)",
    "The receiver is no longer in business": "Action (Sender)",
    "2nd collection attempt. Package not ready. Final collection attempt to be made.": "Notify",
    "Pick-up point unavailable. Delivery to alternative location.": "Notify",
    "Incorrect currency on the invoice": "Action (Sender)",
    "Delivery attempted. No adult signature available. Delivery failed.": "Action (Sender)",
    "Processed for clearance": "No Action",
    "Returned to sender": "Action (Internal)",
    "Driver release - Delivered to a safe place": "No Action",
    "Internal activity scan": "No Action",
    "Shipment exception - Corrective action underway": "Notify",
    "Partial delivery": "Notify",
    "The package is being forwarded to the destination city": "Notify",
    "On hold awaiting collection": "Notify",
    "Delivered to outbuilding": "No Action",
    "Package relabelled": "Notify",
    "Delivered to neighbour": "No Action",
    "Receiver contacted for clearance instructions": "Action (Receiver)",
    "Handover to broker for clearance and delivery": "Notify",
    "Delivery by post - No proof of delivery will be available": "Notify",
    "The contents of your package are subject to export restrictions. Clearance may therefore be delayed": "Escalate to Support",
    "Delivery attempted. Unable to collect tax payment.": "Action (Receiver)",
    "Package reported damaged after delivery": "Notify",
    "Address directions for delivery required": "Action (Receiver)",
    "Packaging damaged. Repacked and forwarded for delivery": "Notify",
    "Delivery failed": "Action (Sender)",
    "Package exceeds maximum weight": "Action",
    "Documents or info requested has now been received and submitted to the regulatory agency for clearance": "Notify",
    "Transit delay": "Notify",
    "Transferred to third party for delivery": "Notify",
    "Delivery attempted. Unable to access the premises for delivery.": "Action (Sender)",
    "Delivery to be re-attempted": "Notify",
    "Delivered to greenhouse": "No Action",
    "Shipment delayed due to a customs gateway hold": "Escalate to Support",
    "Sender tendered the shipment to Carrier after the latest pick-up time for the requested service. A one day delay is likely": "Notify",
    "Manifested, not received": "Escalate to Support",
    "Shipment located and en route to destination": "Notify",
    "Shipment collected from pick-up location": "No Action",
    "Delivery failed due to circumstances outside the carrier's control - Delivery will be rescheduled": "Notify",
    "Package damaged and contents discarded": "Escalate to Support",
    "Inspection of damaged contents scheduled": "Notify",
    "Shipment partially received": "Notify",
    "Package damaged - Refused by receiver": "Action (Sender)",
    "Package too large for delivery": "Escalate to Support",
    "Awaiting further instructions from sender": "Action (Sender)",
    "Rescheduled delivery due to updated address": "Notify",
    "New tracking number assigned to the package": "Notify",
    "Package sent to lost and found": "Escalate to Support",
    "Shipment contains hazardous material": "Escalate to Support",
    "Requested instructions received": "No Action",
    "Package abandoned by sender": "No action",
    "Customs clearance error": "Escalate to Support",
    "Customs clearance cancelled": "Escalate to Support",
    "Awaiting further instructions": "Action (Internal)",
    "Refusal to pay tax": "Action (Receiver)",
    "Some merchandise missing or discarded as damaged": "Escalate to Support",
    "Package returned to sender due to incomplete address": "Action (Sender)",
    "Investigation closed": "No Action",
    "Unable to deliver to pick-up point. Contact carrier for alternative arrangements": "Escalate to Support",
    "Delivery attempted": "Notify",
    "Delivered damaged": "Notify",
    "Misdelivered, parcel retrieved": "Notify",
    "Unable to deliver": "Action (Sender)",
    "The cash on delivery amount is missing from the label": "Action (Internal)",
    "The investigation has been closed as the receiver was unavailable": "No Action",
    "Held in customs after being refused": "Escalate to Support",
    "Payment received during delivery": "No Action",
    "Shipment cancelled": "No Action",
    "Arrival scan": "No Action",
    "Parcel disposed of": "Notify",
    "Shipment on hold - awaiting rest of shipment": "Notify",
    "Delay due to local restrictions": "Notify",
    "Delivered to receiver, return no longer possible": "Notify",
    "Labelling error by sender": "Action (Sender)",
    "Security Inspection completed": "No Action",
    "MSDS required": "Action (Sender)",
    "Handed to partner carrier": "No Action",
    "Label damage or detached. Corrective actions underway": "Notify",
    "Shipment requires manual handling": "Notify",
    "Hs code required": "Action (Receiver)",
    "Awaiting further instructions from receiver": "Action (Receiver)",
    "Special handling required requested": "Notify",
    "Return partially received": "Notify",
    "Insufficient packaging. Corrective actions underway": "Escalate to Support",
    "Return shipment. Sender collection required": "Action (Sender)",
    "Delay due to industrial action": "Notify",
    "Package disposed due to exceeding maximum shelf-life": "Escalate to Support",
    "Shipment refused due to hazardous goods": "Escalate to Support",
    "Alternative vehicle scheduled for this delivery due to size": "Notify",
    "Parcel cannot be located": "Escalate to Support",
    "Unable to deliver to PO box": "Escalate to Support",
    "Delay due to operational reasons": "Notify",
    "Departure Scan": "No Action",
    "Destination scan": "No Action",
    "Hub scan": "No Action",
    "Location scan": "No Action",
    "Origin scan": "No Action",
    "Unload scan": "No Action",
    "Shipment loaded on vehicle": "No Action",
    "We're working to deliver the package as soon as possible": "No Action",
    "Delivered to postbox": "Notify"
}